Metadata-Version: 1.1
Name: nhentai-doujin-downloader
Version: 1.0.5
Summary: A program that downloads Doujins from nHentai as JPEG files
Home-page: UNKNOWN
Author: Kazuto Kirito Kirigaya
Author-email: kirito_kazuto_kirigaya@protonmail.com
License: MIT
Keywords: downloader
Platform: UNKNOWN
Classifier: Development Status :: 5 - Production/Stable
Classifier: Intended Audience :: Developers
Classifier: Operating System :: Microsoft :: Windows :: Windows 10
Classifier: License :: OSI Approved :: MIT License
Classifier: Programming Language :: Python :: 3
